wds_files_general/__init__.py
wds_files_general/sprite_types_gen/battle_city_items/base.ini
wds_files_general/sprite_types_gen/battle_city_items/base.png
wds_files_general/sprite_types_gen/battle_city_items/base_defend_brick.ini
wds_files_general/sprite_types_gen/battle_city_items/base_defend_brick.png
wds_files_general/sprite_types_gen/battle_city_items/base_defend_steel.ini
wds_files_general/sprite_types_gen/battle_city_items/base_defend_steel.png
wds_files_general/sprite_types_gen/battle_city_items/base_grave.ini
wds_files_general/sprite_types_gen/battle_city_items/base_grave.png
wds_files_general/sprite_types_gen/battle_city_items/block_brick.ini
wds_files_general/sprite_types_gen/battle_city_items/block_brick.png
wds_files_general/sprite_types_gen/battle_city_items/block_brick_half.ini
wds_files_general/sprite_types_gen/battle_city_items/block_brick_half.png
wds_files_general/sprite_types_gen/battle_city_items/block_brushes.ini
wds_files_general/sprite_types_gen/battle_city_items/block_bushes.png
wds_files_general/sprite_types_gen/battle_city_items/block_gift_bomb.ini
wds_files_general/sprite_types_gen/battle_city_items/block_gift_bomb.png
wds_files_general/sprite_types_gen/battle_city_items/block_gift_gun.ini
wds_files_general/sprite_types_gen/battle_city_items/block_gift_gun.png
wds_files_general/sprite_types_gen/battle_city_items/block_gift_helmet.ini
wds_files_general/sprite_types_gen/battle_city_items/block_gift_helmet.png
wds_files_general/sprite_types_gen/battle_city_items/block_gift_shovel.ini
wds_files_general/sprite_types_gen/battle_city_items/block_gift_shovel.png
wds_files_general/sprite_types_gen/battle_city_items/block_gift_star.ini
wds_files_general/sprite_types_gen/battle_city_items/block_gift_star.png
wds_files_general/sprite_types_gen/battle_city_items/block_gift_tank.ini
wds_files_general/sprite_types_gen/battle_city_items/block_gift_tank.png
wds_files_general/sprite_types_gen/battle_city_items/block_gift_timer.ini
wds_files_general-0.1.2.dist-info/METADATA
wds_files_general-0.1.2.dist-info/WHEEL
wds_files_general-0.1.2.dist-info/top_level.txt
wds_files_general-0.1.2.dist-info/RECORD
